unittest_hooks-1.0.dev0.dist-info/METADATA
unittest_hooks-1.0.dev0.dist-info/RECORD
unittest_hooks-1.0.dev0.dist-info/WHEEL
unittest_hooks-1.0.dev0.dist-info/entry_points.txt
unittest_hooks-1.0.dev0.dist-info/top_level.txt
unittest_hooks-1.0.dev0.dist-info/zip-safe
unittesthooks/__init__.py
