Metadata-Version: 2.1
Name: unittest-hooks
Version: 1.0.dev0
Summary: pre commit hook for unittest
Home-page: UNKNOWN
Author: Nanthakumar
Author-email: splnanthakumar@gmail.com
License: UNKNOWN
Keywords: unittest pre-commit ut
Platform: UNKNOWN
